softMatrix/Matrix.py
softMatrix/__init__.py
softMatrix-1.0.1.dist-info/LICENCE
softMatrix-1.0.1.dist-info/METADATA
softMatrix-1.0.1.dist-info/WHEEL
softMatrix-1.0.1.dist-info/top_level.txt
softMatrix-1.0.1.dist-info/RECORD
