Metadata-Version: 2.1
Name: softMatrix
Version: 1.0.1
Summary: Un package pour construire des matrices et effectuer toutes les opérations propres aux matrices de manière efficace
Author-email: "Deboua Joseph ~> Deb Josh" <debjojr@gmail.com>
Project-URL: Homepage, https://github.com/Deb-Josh/softMatrix
Classifier: Programming Language :: Python :: 3
Classifier: License :: OSI Approved :: MIT License
Classifier: Operating System :: OS Independent
Requires-Python: >=3.10
License-File: LICENCE
